{
  "layout": {
    "fixed": true
  },
  "permissions": {
    "privateRedirect": "/me",
    "publicRedirect": "/register"
  },
  "footer": {
    "sections": [],
    "socialMediaLinks": {
      "facebook": "https://www.facebook.com/robert.pop.5",
      "medium": "https://medium.com/@robipop22",
      "instagram": "https://www.instagram.com/robipop22/",
      "github": "https://github.com/robipop22",
      "linkedin": "https://www.linkedin.com/in/robert-pop-90a512b6/",
      "twitter": "https://twitter.com/robipop22"
    }
  }
}
